polars_nltk-0.2.2.dist-info/METADATA
polars_nltk-0.2.2.dist-info/WHEEL
polars_nltk/functions.py
polars_nltk/namespace.py
polars_nltk/__init__.py
polars_nltk/polars_nltk.pyd
polars_nltk-0.2.2.dist-info/RECORD
