Metadata-Version: 2.1
Name: polars_nltk
Version: 0.2.2
Classifier: Programming Language :: Rust
Classifier: Programming Language :: Python :: Implementation :: CPython
Classifier: Programming Language :: Python :: Implementation :: PyPy
Requires-Dist: polars >=0.20.7
Author: Barak David <barak1412@gmail.com>
Author-email: Barak David <barak1412@gmail.com>
Requires-Python: >=3.8
